np/server/__init__.py
np/server/server.py
np/server/utils/__init__.py
np/server/utils/alter.py
numpy_flight_server-0.0.2.dist-info/METADATA
numpy_flight_server-0.0.2.dist-info/WHEEL
numpy_flight_server-0.0.2.dist-info/licenses/LICENSE
numpy_flight_server-0.0.2.dist-info/RECORD
