Metadata-Version: 2.4
Name: numpy-flight-server
Version: 0.0.2
Summary: Little numpy/flight server
Project-URL: repository, https://github.com/tschm/numpy-server
Author-email: Thomas Schmelzer <thomas.schmelzer@gmail.com>
License-File: LICENSE
Requires-Python: >=3.10
Requires-Dist: loguru>=0.7.3
Requires-Dist: numpy>=2.2.3
Requires-Dist: pyarrow>=19.0.0
